PyStatsBatteries/Descriptors.py
PyStatsBatteries/ML-Batteries.py
PyStatsBatteries/Management.py
PyStatsBatteries/Test.py
PyStatsBatteries/__init__.py
PyStatsBatteries-0.0.3.dist-info/METADATA
PyStatsBatteries-0.0.3.dist-info/WHEEL
PyStatsBatteries-0.0.3.dist-info/top_level.txt
PyStatsBatteries-0.0.3.dist-info/RECORD
