Metadata-Version: 2.1
Name: PyStatsBatteries
Version: 0.0.3
Summary: This library provides several tools for your Python dataframes, such as graphics, Machine Learning alogrithms, and data analysis tools. All these functions will be applied to electrochemical Lithium-ion batteries.
Home-page: https://github.com/MarcDuquesnoy/PyStatsBatteries
Author: Marc Duquesnoy
Author-email: marc.duquesnoy@u-picardie.fr
License: GNU Public License
Platform: UNKNOWN
Classifier: Programming Language :: Python
Classifier: Development Status :: 1 - Planning
Classifier: License :: OSI Approved
Classifier: Natural Language :: English
Classifier: Operating System :: OS Independent
Classifier: Programming Language :: Python :: 3.7
Classifier: Topic :: Communications
Requires-Dist: pandas
Requires-Dist: matplotlib
Requires-Dist: seaborn
Requires-Dist: scikit-learn
Requires-Dist: tensorflow
